harshit/__init__.py
harshit/harshit.py
harshit-0.0.1.dist-info/LICENSE
harshit-0.0.1.dist-info/METADATA
harshit-0.0.1.dist-info/WHEEL
harshit-0.0.1.dist-info/top_level.txt
harshit-0.0.1.dist-info/RECORD
