Metadata-Version: 2.1
Name: harshit
Version: 0.0.1
Summary: It squares the number
Home-page: https://github.com/shadow-python/pip-package
Author: Harshit Mehra
Author-email: harshitmeh111@gmail.com
License: MIT
Platform: UNKNOWN
Classifier: License :: OSI Approved :: MIT License
Classifier: Programming Language :: Python :: 3
